openapi_llm/__init__.py
openapi_llm/utils.py
openapi_llm/client/__init__.py
openapi_llm/client/config.py
openapi_llm/client/openapi.py
openapi_llm/client/openapi_async.py
openapi_llm/core/__init__.py
openapi_llm/core/auth.py
openapi_llm/core/provider.py
openapi_llm/core/schema_conversion.py
openapi_llm/core/spec.py
openapi_llm/providers/__init__.py
openapi_llm/providers/anthropic.py
openapi_llm/providers/cohere.py
openapi_llm/providers/openai.py
openapi_llm-0.4.3.dist-info/METADATA
openapi_llm-0.4.3.dist-info/WHEEL
openapi_llm-0.4.3.dist-info/licenses/LICENSE
openapi_llm-0.4.3.dist-info/RECORD
